.gitignore
LICENSE
MANIFEST.in
README.md
README.rst
setup.py
astride/__init__.py
astride/detect.py
astride.egg-info/PKG-INFO
astride.egg-info/SOURCES.txt
astride.egg-info/dependency_links.txt
astride.egg-info/requires.txt
astride.egg-info/top_level.txt
astride/datasets/__init__.py
astride/datasets/base.py
astride/datasets/C/README.txt
astride/datasets/C/streak.tgz
astride/datasets/samples/long.fits
astride/test/__init__.py
astride/test/run.py
astride/utils/__init__.py
astride/utils/edge.py
astride/utils/logger.py
astride/utils/misc.py
astride/utils/outlier.py