Metadata-Version: 1.1
Name: astride
Version: 0.3.5
Summary: Automated Streak Detection for High Velocity Objects
Home-page: https://github.com/dwkim78/astride
Author: Dae-Won Kim
Author-email: dwkim78@gmail.com
License: MIT
Keywords: astronomy,image,streak,satellite,meteor,NEO,fast-moving objects,boundary-tracing,contour-tracing
Platform: any
Classifier: Development Status :: 4 - Beta
Classifier: Intended Audience :: Science/Research
Classifier: License :: OSI Approved :: MIT License
Classifier: Natural Language :: English
Classifier: Operating System :: OS Independent
Classifier: Programming Language :: Python :: 3.5
Classifier: Topic :: Scientific/Engineering :: Astronomy
